MANIFEST.in
requirements.txt
setup.py
socialschools_cms/__init__.py
socialschools_cms/base_settings.py
socialschools_cms/models.py
socialschools_cms/tests.py
socialschools_cms/views.py
socialschools_cms.egg-info/PKG-INFO
socialschools_cms.egg-info/SOURCES.txt
socialschools_cms.egg-info/dependency_links.txt
socialschools_cms.egg-info/not-zip-safe
socialschools_cms.egg-info/requires.txt
socialschools_cms.egg-info/top_level.txt
socialschools_cms/locale/nl/LC_MESSAGES/django.mo
socialschools_cms/locale/nl/LC_MESSAGES/django.po
socialschools_cms/plugins/__init__.py
socialschools_cms/plugins/file/__init__.py
socialschools_cms/plugins/file/cms_plugins.py
socialschools_cms/plugins/file/models.py
socialschools_cms/plugins/file/migrations/0001_initial.py
socialschools_cms/plugins/file/migrations/0002_freeze.py
socialschools_cms/plugins/file/migrations/0003_publisher.py
socialschools_cms/plugins/file/migrations/0004_table_rename.py
socialschools_cms/plugins/file/migrations/0005_publisher2.py
socialschools_cms/plugins/file/migrations/__init__.py
socialschools_cms/plugins/file/templates/cms/plugins/file.html
socialschools_cms/static/css/bootstrap-image-gallery.css.less
socialschools_cms/static/css/bootstrap-overrides.less
socialschools_cms/static/css/carousels.less
socialschools_cms/static/css/django-cms.less
socialschools_cms/static/css/footer.less
socialschools_cms/static/css/navbars.less
socialschools_cms/static/css/pictures.less
socialschools_cms/static/css/post.less
socialschools_cms/static/css/site.less
socialschools_cms/static/css/styles.css
socialschools_cms/static/css/styles.less
socialschools_cms/static/css/variables.less
socialschools_cms/static/css/widgets.less
socialschools_cms/static/css/bootstrap/alerts.less
socialschools_cms/static/css/bootstrap/badges.less
socialschools_cms/static/css/bootstrap/bootstrap.less
socialschools_cms/static/css/bootstrap/breadcrumbs.less
socialschools_cms/static/css/bootstrap/button-groups.less
socialschools_cms/static/css/bootstrap/buttons.less
socialschools_cms/static/css/bootstrap/carousel.less
socialschools_cms/static/css/bootstrap/close.less
socialschools_cms/static/css/bootstrap/code.less
socialschools_cms/static/css/bootstrap/component-animations.less
