Metadata-Version: 1.0
Name: socialschools-cms
Version: 1.5.4
Summary: SocialSchools CMS app with defaults for django-cms
Home-page: UNKNOWN
Author: Pratik Vyas
Author-email: pratik.vyas@changer.nl
License: UNKNOWN
Platform: UNKNOWN
